MANIFEST.in
README.rst
setup.py
colorful_hieroglyph_theme/__init__.py
colorful_hieroglyph_theme.egg-info/PKG-INFO
colorful_hieroglyph_theme.egg-info/SOURCES.txt
colorful_hieroglyph_theme.egg-info/dependency_links.txt
colorful_hieroglyph_theme.egg-info/not-zip-safe
colorful_hieroglyph_theme.egg-info/requires.txt
colorful_hieroglyph_theme.egg-info/top_level.txt