Metadata-Version: 1.0
Name: colorful-hieroglyph-theme
Version: 0.1
Summary: A simple, colorful hieroglyph theme
Home-page: https://github.com/lucywyman/colorful-hieroglyph-theme
Author: Lucy Wyman
Author-email: lucyw@osuosl.org
License: UNKNOWN
Keywords: hieroglyph extension theme
Platform: UNKNOWN
